MANIFEST.in
README.md
pyproject.toml
setup.cfg
setup.py
src/first_python_package.egg-info/PKG-INFO
src/first_python_package.egg-info/SOURCES.txt
src/first_python_package.egg-info/dependency_links.txt
src/first_python_package.egg-info/entry_points.txt
src/first_python_package.egg-info/requires.txt
src/first_python_package.egg-info/top_level.txt
src/impkg/__init__.py
src/impkg/data.json
src/impkg/harmonic_mean.c
src/impkg/harmonic_mean.pyx
src/impkg/harmony.py
src/impkg/hello.py
src/impkg/py.typed
src/impkg/__pycache__/harmonic_mean.cpython-310.pyc
test/test_harmonic_mean.py